butrand/__init__.py
butrand/core.py
butrand-0.0.1.dist-info/licenses/LICENSE
butrand-0.0.1.dist-info/METADATA
butrand-0.0.1.dist-info/WHEEL
butrand-0.0.1.dist-info/top_level.txt
butrand-0.0.1.dist-info/RECORD
