Metadata-Version: 2.4
Name: butrand
Version: 0.0.1
Summary: Fast and chaotic random number generator based on butterfly effect
Home-page: https://github.com/OmeraGod/butrand
Author: Bùi Phong Phú
Author-email: omerasutvailworkit@gmail.com
Classifier: Programming Language :: Python :: 3
Classifier: License :: OSI Approved :: MIT License
Classifier: Operating System :: OS Independent
Requires-Python: >=3.6
License-File: LICENSE
Dynamic: author
Dynamic: author-email
Dynamic: classifier
Dynamic: description
Dynamic: description-content-type
Dynamic: home-page
Dynamic: license-file
Dynamic: requires-python
Dynamic: summary
